Metadata-Version: 2.1
Name: ituscraper-py
Version: 0.1a0
Summary: Python library for scraping data from Istanbul Technical University websites.
Home-page: https://github.com/SerhanCeetin/ituscraper-py
Author: SerhanCeetin
Author-email: ceetinserhan@gmail.com
License: MIT
Requires-Python: >=3.8
License-File: LICENSE
